slack_entities/__init__.py
slack_entities/client/__init__.py
slack_entities/client/client.py
slack_entities/entities/__init__.py
slack_entities/entities/action.py
slack_entities/entities/channel.py
slack_entities/entities/dialog.py
slack_entities/entities/event.py
slack_entities/entities/incoming_message.py
slack_entities/entities/outcoming_message.py
slack_entities/entities/resource.py
slack_entities/entities/team.py
slack_entities/entities/user.py
slack_entities/exceptions/__init__.py
slack_entities/exceptions/exceptions.py
slack_entities/tests/entities/__init__.py
slack_entities/tests/entities/test_action.py
slack_entities/tests/entities/test_channel.py
slack_entities/tests/entities/test_event.py
slack_entities/tests/entities/test_team.py
slack_entities/tests/entities/test_user.py
slack_entities-0.0.24.1.dist-info/METADATA
slack_entities-0.0.24.1.dist-info/RECORD
slack_entities-0.0.24.1.dist-info/WHEEL
slack_entities-0.0.24.1.dist-info/top_level.txt
