Metadata-Version: 2.1
Name: slack-entities
Version: 0.0.24.1
Summary: Package for more convenient work with Slack API
Home-page: https://github.com/chimplie/slack_entities
Author: Oleh Zorenko
Author-email: oleh@chimplie.com
License: UNKNOWN
Platform: UNKNOWN
Classifier: Programming Language :: Python :: 3
Classifier: License :: OSI Approved :: MIT License
Classifier: Operating System :: OS Independent
Requires-Dist: slackclient (==1.2.1)
